ez/__init__.py
ez/eztest.py
ez/struct.py
ezmanager-0.0.0a1.dist-info/LICENSE
ezmanager-0.0.0a1.dist-info/METADATA
ezmanager-0.0.0a1.dist-info/WHEEL
ezmanager-0.0.0a1.dist-info/top_level.txt
ezmanager-0.0.0a1.dist-info/RECORD
