Metadata-Version: 2.1
Name: ezmanager
Version: 0.0.0a1
Summary: Easily usable tools for programming
Home-page: https://github.com/EzManager/Ez
Author: ForestHouse
Author-email: foresthouse2316@gmail.com
License: MIT
Platform: UNKNOWN
License-File: LICENSE
